github_issue_prompter/__init__.py
github_issue_prompter/command.py
github_issue_prompter/constants.py
github_issue_prompter/github_gql.py
github_issue_prompter/github_rest.py
github_issue_prompter/prompter.py
github_issue_prompter/py.typed
github_issue_prompter/status.py
github_issue_prompter/types.py
github_issue_prompter-0.0.5.dist-info/LICENSE
github_issue_prompter-0.0.5.dist-info/METADATA
github_issue_prompter-0.0.5.dist-info/WHEEL
github_issue_prompter-0.0.5.dist-info/entry_points.txt
github_issue_prompter-0.0.5.dist-info/top_level.txt
github_issue_prompter-0.0.5.dist-info/RECORD
