Metadata-Version: 2.1
Name: github_issue_prompter
Version: 0.0.5
Summary: Use AI to find GitHub issue's that you can work on (even if the issue's appear active)!
Author-email: Lukas Twist <itsluketwist@gmail.com>
License: MIT License
Project-URL: Homepage, https://github.com/itsluketwist/github-issue-prompter
Project-URL: Code, https://github.com/itsluketwist/github-issue-prompter
Project-URL: Download, https://github.com/itsluketwist/github-issue-prompter/tags
Keywords: github,issue,prompter,openai
Classifier: License :: OSI Approved :: MIT License
Classifier: Programming Language :: Python
Classifier: Programming Language :: Python :: 3
Requires-Python: >=3.10
License-File: LICENSE
Requires-Dist: requests ~=2.31.0
Requires-Dist: openai ~=1.7.1
Provides-Extra: dev
Requires-Dist: pre-commit ; extra == 'dev'
Requires-Dist: pytest ; extra == 'dev'
